Workbook

Sheet 汇总
A3: 圣天地公寓锅炉工人员成本（2024年度）
A5: 月份 | B5: 人数 | C5: 薪资 | D5: 五险一金 | E5: 合计 | F5: 备注
A6: 1月 | B6: ='2023.12'!B9 -> 3 | C6: ='2023.12'!C9 -> 18462.1 | D6: ='2023.12'!E9 -> 2378.86 | E6: =SUM(C6:D6) -> 20840.96
A7: 2月 | B7: ='2024.01'!B9 -> 3 | C7: ='2024.01'!C9+'2024.01'!D9 -> 44944.8 | D7: ='2024.01'!E9 -> 2378.86 | E7: =SUM(C7:D7) -> 47323.66
A8: 3月 | B8: ='2024.02'!B9 -> 3 | C8: ='2024.02'!C9+'2024.02'!D9 -> 22919.5 | D8: ='2024.02'!E9 -> 2378.86 | E8: =SUM(C8:D8) -> 25298.36
A9: 4月 | B9: ='2024.03'!B9 -> 3 | C9: ='2024.03'!C9+'2024.03'!D9 -> 17800 | D9: ='2024.03'!E9 -> 2378.86 | E9: =SUM(C9:D9) -> 20178.86
A10: 5月 | B10: ='2024.04'!B9 -> 3 | C10: ='2024.04'!C9+'2024.04'!D9 -> 18793.1 | D10: ='2024.04'!E9 -> 2378.86 | E10: =SUM(C10:D10) -> 21171.96
A11: 6月 | B11: ='2024.05'!B9 -> 3 | C11: ='2024.05'!C9+'2024.05'!D9 -> 19393.1 | D11: ='2024.05'!E9 -> 2378.86 | E11: =SUM(C11:D11) -> 21771.96
A12: 7月 | B12: ='2024.06'!B9 -> 3 | C12: ='2024.06'!C9+'2024.06'!D9 -> 21623 | D12: ='2024.06'!E9 -> 5738.19 | E12: =SUM(C12:D12) -> 27361.19
A13: 8月 | B13: ='2024.07'!B9 -> 3 | C13: ='2024.07'!C9+'2024.07'!D9 -> 18100 | D13: ='2024.07'!E9 -> 4604.68 | E13: =SUM(C13:D13) -> 22704.68
A14: 9月 | B14: ='2024.08'!B9 -> 3 | C14: ='2024.08'!C9+'2024.08'!D9 -> 25493 | D14: ='2024.08'!E9 -> 4570.64 | E14: =SUM(C14:D14) -> 30063.64
A15: 10月 | B15: ='2024.09'!B9 -> 3 | C15: ='2024.09'!C9+'2024.09'!D9 -> 19155.1 | D15: ='2024.09'!E9 -> 4570.64 | E15: =SUM(C15:D15) -> 23725.74
A16: 11月 | B16: ='2024.10'!B9 -> 3 | C16: ='2024.10'!C9+'2024.10'!D9 -> 22517 | D16: ='2024.10'!E9 -> 4570.64 | E16: =SUM(C16:D16) -> 27087.64
A17: 12月 | B17: ='2024.11'!B8 -> 2 | C17: ='2024.11'!C8+'2024.11'!D8 -> 15400 | D17: ='2024.11'!E8 -> 4570.64 | E17: =SUM(C17:D17) -> 19970.64 | F17: 张标协议加班，算2人
A18: 合计： | B18: =SUM(B6:B17) -> 35 | C18: =SUM(C6:C17) -> 264600.7 | D18: =SUM(D6:D17) -> 42898.59 | E18: =SUM(E6:E17) -> 307499.29

Sheet 2023.12
A3: 圣天地公寓锅炉工人员成本（2023年12月）
A5: 姓名 | B5: 员工人数 | C5: 工资 | D5: 其他 | E5: 公司四金 | F5: 合计 | G5: 备注
A6: 王贵阳 | B6: 1 | C6: 6000 | D6: 0 | E6: =1955.86+423 -> 2378.86 | F6: =SUM(C6:E6) -> 8378.86
A7: 马春生 | B7: 1 | C7: 6562.1 | D7: 0 | E7: 0 | F7: =SUM(C7:E7) -> 6562.1
A8: 王文乾 | B8: 1 | C8: 5900 | D8: 0 | E8: 0 | F8: =SUM(C8:E8) -> 5900
A9: 合计： | B9: =SUM(B6:B8) -> 3 | C9: =SUM(C6:C8) -> 18462.1 | D9: =SUM(D6:D8) -> 0 | E9: =SUM(E6:E8) -> 2378.86 | F9: =SUM(F6:F8) -> 20840.96
A12: 人员费用合计 | E12: =F9 -> 20840.96
G15: 制表日期：2024/1/10

Sheet 2024.01
A3: 圣天地公寓锅炉工人员成本（2024年01月）
A5: 姓名 | B5: 员工人数 | C5: 工资 | D5: 年终奖 | E5: 公司四金 | F5: 合计 | G5: 备注
A6: 王贵阳 | B6: 1 | C6: 7013.8 | D6: 9400 | E6: =1955.86+423 -> 2378.86 | F6: =SUM(C6:E6) -> 18792.66
A7: 马春生 | B7: 1 | C7: 5900 | D7: 8200 | E7: 0 | F7: =SUM(C7:E7) -> 14100
A8: 王文乾 | B8: 1 | C8: 6231 | D8: 8200 | E8: 0 | F8: =SUM(C8:E8) -> 14431
A9: 合计： | B9: =SUM(B6:B8) -> 3 | C9: =SUM(C6:C8) -> 19144.8 | D9: =SUM(D6:D8) -> 25800 | E9: =SUM(E6:E8) -> 2378.86 | F9: =SUM(F6:F8) -> 47323.66
A12: 人员费用合计 | E12: =F9 -> 47323.66
G15: 制表日期：2024/2/10

Sheet 2024.02
A3: 圣天地公寓锅炉工人员成本（2024年02月）
A5: 姓名 | B5: 员工人数 | C5: 工资 | D5: 其他 | E5: 公司四金 | F5: 合计 | G5: 备注
A6: 王贵阳 | B6: 1 | C6: 8140.2 | D6: 0 | E6: =1955.86+423 -> 2378.86 | F6: =SUM(C6:E6) -> 10519.06
A7: 马春生 | B7: 1 | C7: 7555.2 | D7: 0 | E7: 0 | F7: =SUM(C7:E7) -> 7555.2
A8: 王文乾 | B8: 1 | C8: 7224.1 | D8: 0 | E8: 0 | F8: =SUM(C8:E8) -> 7224.1
A9: 合计： | B9: =SUM(B6:B8) -> 3 | C9: =SUM(C6:C8) -> 22919.5 | D9: =SUM(D6:D8) -> 0 | E9: =SUM(E6:E8) -> 2378.86 | F9: =SUM(F6:F8) -> 25298.36
A12: 人员费用合计 | E12: =F9 -> 25298.36
G15: 制表日期：2024/3/10

Sheet 2024.03
A3: 圣天地公寓锅炉工人员成本（2024年3月）
A5: 姓名 | B5: 员工人数 | C5: 工资 | D5: 其他 | E5: 公司四金 | F5: 合计 | G5: 备注
A6: 王贵阳 | B6: 1 | C6: 6000 | D6: 0 | E6: =1955.86+423 -> 2378.86 | F6: =SUM(C6:E6) -> 8378.86
A7: 马春生 | B7: 1 | C7: 5900 | D7: 0 | E7: 0 | F7: =SUM(C7:E7) -> 5900
A8: 王文乾 | B8: 1 | C8: 5900 | D8: 0 | E8: 0 | F8: =SUM(C8:E8) -> 5900
A9: 合计： | B9: =SUM(B6:B8) -> 3 | C9: =SUM(C6:C8) -> 17800 | D9: =SUM(D6:D8) -> 0 | E9: =SUM(E6:E8) -> 2378.86 | F9: =SUM(F6:F8) -> 20178.86
A12: 人员费用合计 | E12: =F9 -> 20178.86
G15: 制表日期：2024/4/10

Sheet 2024.04
A3: 圣天地公寓锅炉工人员成本（2024年4月）
A5: 姓名 | B5: 员工人数 | C5: 工资 | D5: 其他 | E5: 公司四金 | F5: 合计 | G5: 备注
A6: 王贵阳 | B6: 1 | C6: 6000 | D6: 0 | E6: =1955.86+423 -> 2378.86 | F6: =SUM(C6:E6) -> 8378.86
A7: 马春生 | B7: 1 | C7: 6562.1 | D7: 0 | E7: 0 | F7: =SUM(C7:E7) -> 6562.1
A8: 王文乾 | B8: 1 | C8: 6231 | D8: 0 | E8: 0 | F8: =SUM(C8:E8) -> 6231
A9: 合计： | B9: =SUM(B6:B8) -> 3 | C9: =SUM(C6:C8) -> 18793.1 | D9: =SUM(D6:D8) -> 0 | E9: =SUM(E6:E8) -> 2378.86 | F9: =SUM(F6:F8) -> 21171.96
A12: 人员费用合计 | E12: =F9 -> 21171.96
G15: 制表日期：2024/5/10

Sheet 2024.05
A3: 圣天地公寓锅炉工人员成本（2024年5月）
A5: 姓名 | B5: 员工人数 | C5: 工资 | D5: 其他 | E5: 公司四金 | F5: 合计 | G5: 备注
A6: 王贵阳 | B6: 1 | C6: 6300 | D6: 0 | E6: =1955.86+423 -> 2378.86 | F6: =SUM(C6:E6) -> 8678.86
A7: 马春生 | B7: 1 | C7: 6531 | D7: 0 | E7: 0 | F7: =SUM(C7:E7) -> 6531
A8: 王文乾 | B8: 1 | C8: 6562.1 | D8: 0 | E8: 0 | F8: =SUM(C8:E8) -> 6562.1
A9: 合计： | B9: =SUM(B6:B8) -> 3 | C9: =SUM(C6:C8) -> 19393.1 | D9: =SUM(D6:D8) -> 0 | E9: =SUM(E6:E8) -> 2378.86 | F9: =SUM(F6:F8) -> 21771.96
A12: 人员费用合计 | E12: =F9 -> 21771.96
G15: 制表日期：2024/6/10

Sheet 2024.06
A3: 圣天地公寓锅炉工人员成本（2024年6月）
A5: 姓名 | B5: 员工人数 | C5: 工资 | D5: 其他 | E5: 公司四金 | F5: 合计 | G5: 备注
A6: 王贵阳 | B6: 1 | C6: 6750.6 | D6: 0 | E6: =1955.86+423 -> 2378.86 | F6: =SUM(C6:E6) -> 9129.46
A7: 马春生 | B7: 1 | C7: 6531 | D7: 0 | E7: 0 | F7: =SUM(C7:E7) -> 6531
A8: 史金军 | B8: 1 | C8: 8341.4 | D8: 0 | E8: =2744.33+615 -> 3359.33 | F8: =SUM(C8:E8) -> 11700.73
A9: 合计： | B9: =SUM(B6:B8) -> 3 | C9: =SUM(C6:C8) -> 21623 | D9: =SUM(D6:D8) -> 0 | E9: =SUM(E6:E8) -> 5738.19 | F9: =SUM(F6:F8) -> 27361.19
A12: 人员费用合计 | E12: =F9 -> 27361.19
G15: 制表日期：2024/7/10

Sheet 2024.07
A3: 圣天地公寓锅炉工人员成本（2024年7月）
A5: 姓名 | B5: 员工人数 | C5: 工资 | D5: 其他 | E5: 公司四金 | F5: 合计 | G5: 备注
A6: 王贵阳 | B6: 1 | C6: 6300 | D6: 0 | E6: =1955.86+423 -> 2378.86 | F6: =SUM(C6:E6) -> 8678.86
A7: 马春生 | B7: 1 | C7: 6200 | D7: 0 | E7: 0 | F7: =SUM(C7:E7) -> 6200
A8: 张标 | B8: 1 | C8: 5600 | D8: 0 | E8: =1901.82+324 -> 2225.82 | F8: =SUM(C8:E8) -> 7825.82
A9: 合计： | B9: =SUM(B6:B8) -> 3 | C9: =SUM(C6:C8) -> 18100 | D9: =SUM(D6:D8) -> 0 | E9: =SUM(E6:E8) -> 4604.68 | F9: =SUM(F6:F8) -> 22704.68
A12: 人员费用合计 | E12: =F9 -> 22704.68
G15: 制表日期：2024/8/10

Sheet 2024.08
A3: 圣天地公寓锅炉工人员成本（2024年8月）
A5: 姓名 | B5: 员工人数 | C5: 工资 | D5: 其他 | E5: 公司四金 | F5: 合计 | G5: 备注
A6: 王贵阳 | B6: 1 | C6: 9300 | D6: 0 | E6: =1901.82+443 -> 2344.82 | F6: =SUM(C6:E6) -> 11644.82
A7: 马春生 | B7: 1 | C7: 9200 | D7: 0 | E7: 0 | F7: =SUM(C7:E7) -> 9200
A8: 张标 | B8: 1 | C8: 6993 | D8: 0 | E8: =1901.82+324 -> 2225.82 | F8: =SUM(C8:E8) -> 9218.82
A9: 合计： | B9: =SUM(B6:B8) -> 3 | C9: =SUM(C6:C8) -> 25493 | D9: =SUM(D6:D8) -> 0 | E9: =SUM(E6:E8) -> 4570.64 | F9: =SUM(F6:F8) -> 30063.64
A12: 人员费用合计 | E12: =F9 -> 30063.64
G15: 制表日期：2024/9/10

Sheet 2024.09
A3: 圣天地公寓锅炉工人员成本（2024年9月）
A5: 姓名 | B5: 员工人数 | C5: 工资 | D5: 其他 | E5: 公司四金 | F5: 合计 | G5: 备注
A6: 王贵阳 | B6: 1 | C6: 6000 | D6: 0 | E6: =1901.82+443 -> 2344.82 | F6: =SUM(C6:E6) -> 8344.82
A7: 马春生 | B7: 1 | C7: 6924.1 | D7: 0 | E7: 0 | F7: =SUM(C7:E7) -> 6924.1
A8: 张标 | B8: 1 | C8: 6231 | D8: 0 | E8: =1901.82+324 -> 2225.82 | F8: =SUM(C8:E8) -> 8456.82
A9: 合计： | B9: =SUM(B6:B8) -> 3 | C9: =SUM(C6:C8) -> 19155.1 | D9: =SUM(D6:D8) -> 0 | E9: =SUM(E6:E8) -> 4570.64 | F9: =SUM(F6:F8) -> 23725.74
A12: 人员费用合计 | E12: =F9 -> 23725.74
G15: 制表日期：2024/10/10

Sheet 2024.10
A3: 圣天地公寓锅炉工人员成本（2024年10月）
A5: 姓名 | B5: 员工人数 | C5: 工资 | D5: 其他 | E5: 公司四金 | F5: 合计 | G5: 备注
A6: 王贵阳 | B6: 1 | C6: 7013.8 | D6: 0 | E6: =1901.82+443 -> 2344.82 | F6: =SUM(C6:E6) -> 9358.62
A7: 马春生 | B7: 1 | C7: 8879.1 | D7: 0 | E7: 0 | F7: =SUM(C7:E7) -> 8879.1
A8: 张标 | B8: 1 | C8: 6624.1 | D8: 0 | E8: =1901.82+324 -> 2225.82 | F8: =SUM(C8:E8) -> 8849.92
A9: 合计： | B9: =SUM(B6:B8) -> 3 | C9: =SUM(C6:C8) -> 22517 | D9: =SUM(D6:D8) -> 0 | E9: =SUM(E6:E8) -> 4570.64 | F9: =SUM(F6:F8) -> 27087.64
A12: 人员费用合计 | E12: =F9 -> 27087.64
G15: 制表日期：2024/11/10

Sheet 2024.11
A3: 圣天地公寓锅炉工人员成本（2024年11月）
A5: 姓名 | B5: 员工人数 | C5: 工资 | D5: 其他 | E5: 公司四金 | F5: 合计 | G5: 备注
A6: 王贵阳 | B6: 1 | C6: 6000 | D6: 0 | E6: =1901.82+443 -> 2344.82 | F6: =SUM(C6:E6) -> 8344.82
A7: 张标 | B7: 1 | C7: 9400 | D7: 0 | E7: =1901.82+324 -> 2225.82 | F7: =SUM(C7:E7) -> 11625.82
A8: 合计： | B8: =SUM(B6:B7) -> 2 | C8: =SUM(C6:C7) -> 15400 | D8: =SUM(D6:D7) -> 0 | E8: =SUM(E6:E7) -> 4570.64 | F8: =SUM(F6:F7) -> 19970.64
A11: 人员费用合计 | E11: =F8 -> 19970.64
G14: 制表日期：2024/12/10

Sheet Sheet3
A1: 大厦供电收支表 | I1: 灰色是公式，填没有色的空格
A3: 项目 | D3: 电费账单 单价 | E3: 供电合理线损费用等 | F3: 电费单价 （含合理线损费等） | G3: 用电量 | H3: 应收金额
A4: 收入 | B4: 合并开具13%发票 | C4: 电费 | D4: 0.96 | E4: =D4*0.1 -> 0.096 | F4: =D4+E4 -> 1.056 | G4: 500 | H4: =G4*F4 -> 528
C5: 小计 | D5: =D4 -> 0.96 | E5: =E4 -> 0.096 | F5: =F4 -> 1.056 | G5: =G4 -> 500 | H5: =H4 -> 528
C6: 转供电设施维护费 | D6: =D4 -> 0.96 | E6: =D6*0.1 -> 0.096 | F6: =0.2-E6 -> 0.104 | G6: 300 | H6: =G6*F6 -> 31.2
C7: 小计 | D7: =SUM(D6) -> 0.96 | E7: =SUM(E6) -> 0.096 | F7: =SUM(F6) -> 0.104 | G7: =SUM(G6) -> 300 | H7: =H6 -> 31.2
C8: 合计 | G8: =G5+G7 -> 800 | H8: =H7+H5 -> 559.2
B9: 分开开具13%和6%发票 | C9: 电费 | D9: =D4 -> 0.96 | E9: =D9*0.1 -> 0.096 | F9: =D9+E9 -> 1.056 | G9: 500 | H9: =ROUND(D9*G9*1.1,2) -> 528
C10: 小计 | D10: =D9 -> 0.96 | E10: =E9 -> 0.096 | F10: =F9 -> 1.056 | G10: =G9 -> 500 | H10: =H9 -> 528
C11: 转供电设施维护费 | D11: =D9 -> 0.96 | E11: =D11*0.1 -> 0.096 | F11: =0.2-$E$11 -> 0.104 | G11: 300 | H11: =G11*F11 -> 31.2
C12: 小计 | D12: =D11 -> 0.96 | E12: =E11 -> 0.096 | F12: =F11 -> 0.104 | G12: =G11 -> 300 | H12: =H11 -> 31.2
C13: 合计 | G13: =G10+G12 -> 800 | H13: =H10+H12 -> 559.2
B14: 总计 | G14: =G13+G8 -> 1600 | H14: =H13+H8 -> 1118.4
B15: 项目 | C15: 用电量 | D15: 电费账单 单价 | E15: 金额
A16: 支出 | B16: 应付电费
